{
  "id": 230,
  "created_at": "2013-03-24 08:56:38 UTC",
  "updated_at": "2013-03-24 08:56:38 UTC",
  "last_record_at": "2013-04-02 00:00:00 UTC",
  "title": "Looney's rain guage",
  "town_suburb": "",
  "country": null,
  "latitude": null,
  "longitude": null,
  "precipitation": {
    "2013": {
      "1": {
        "13": 13.5,
        "19": 2.5,
        "20": 1.8,
        "22": 1.5,
        "25": 16.0,
        "26": 6.0,
        "27": 25.5,
        "28": 67.5
      },
      "2": {
        "1": 27.0,
        "9": 11.5,
        "13": 3.0,
        "18": 3.0,
        "22": 6.5,
        "23": 17.0,
        "25": 3.5,
        "28": 32.0
      },
      "3": {
        "1": 40.0,
        "2": 0.8,
        "23": 2.5,
        "28": 3.5
      },
      "4": {
        "2": 3.4
      }
    }
  },
  "temperatureMin": {
  },
  "temperatureMax": {
  }
}