{
  "id": 250,
  "created_at": "2013-07-19T23:18:28.000Z",
  "updated_at": "2013-07-19T23:18:28.000Z",
  "title": "Wimmera Highway",
  "street_address": "",
  "town_suburb": "Rupanyup",
  "region": "",
  "country": null,
  "latitude": null,
  "longitude": null,
  "precipitation": {
    "2015": {
      "1": {
        "14": 13.5,
        "13": 28.5,
        "11": 0.5,
        "10": 15.0,
        "9": 4.0,
        "5": 2.0
      }
    },
    "2014": {
      "11": {
        "24": 2.0,
        "23": 2.0,
        "22": 2.5,
        "16": 13.0,
        "1": 1.75
      },
      "10": {
        "27": 1.5,
        "23": 6.5,
        "14": 4.0,
        "7": 2.0
      },
      "9": {
        "25": 6.25,
        "9": 2.0,
        "2": 6.5
      },
      "8": {
        "1": 6.5
      },
      "7": {
        "30": 3.5,
        "26": 3.0,
        "25": 2.0,
        "24": 6.0,
        "18": 1.0,
        "17": 1.5,
        "16": 2.5,
        "15": 10.0,
        "9": 5.5
      },
      "6": {
        "28": 4.0,
        "25": 4.0,
        "22": 1.5,
        "21": 3.5,
        "16": 5.0,
        "5": 4.0,
        "1": 10.0
      },
      "5": {
        "27": 4.0,
        "25": 3.5,
        "23": 10.0,
        "10": 10.5
      },
      "4": {
        "10": 14.0,
        "9": 20.0
      },
      "1": {
        "24": 1.0,
        "2": 5.25
      }
    },
    "2013": {
      "11": {
        "13": 10.5,
        "8": 4.0
      },
      "10": {
        "28": 2.75,
        "23": 37.5,
        "14": 2.5,
        "3": 2.0,
        "1": 2.5
      },
      "9": {
        "26": 15.5,
        "22": 5.5,
        "20": 5.6,
        "17": 0.5,
        "16": 5.5,
        "14": 7.5,
        "6": 0.25
      },
      "8": {
        "31": 5.75,
        "30": 1.5,
        "24": 1.0,
        "23": 2.0,
        "22": 4.0,
        "20": 9.0,
        "17": 9.0,
        "13": 9.25,
        "8": 10.0,
        "6": 4.5,
        "5": 7.5
      },
      "7": {
        "29": 8.0,
        "20": 9.0,
        "18": 4.6
      }
    }
  },
  "temperatureMin": {

  },
  "temperatureMax": {

  }
}